scotusutils/__init__.py
scotusutils/analysis.py
scotusutils/configtools.py
scotusutils/dbtools.py
scotusutils/documents.py
scotusutils/process.py
scotusutils/utils.py
scotusutils/webscrape.py
scotusutils-0.2.dev0.data/scripts/scotus-data-init
scotusutils-0.2.dev0.dist-info/LICENSE
scotusutils-0.2.dev0.dist-info/METADATA
scotusutils-0.2.dev0.dist-info/WHEEL
scotusutils-0.2.dev0.dist-info/top_level.txt
scotusutils-0.2.dev0.dist-info/RECORD
