Metadata-Version: 2.1
Name: scotusutils
Version: 0.2.dev0
Summary: SCOTUS Analysis Tools
Home-page: https://gitlab.com/immersinn/scotusutils
Author: Thomas Richardson II
Author-email: immersinn@gmail.com
License: Creative Commons Attribution-Noncommercial-Share Alike license
Platform: UNKNOWN
Classifier: Programming Language :: Python :: 3
Classifier: License :: OSI Approved :: MIT License
Classifier: Operating System :: OS Independent
